pydrill/__init__.py
pydrill/compat.py
pydrill/exceptions.py
pydrill/serializer.py
pydrill/transport.py
pydrill/client/__init__.py
pydrill/client/result.py
pydrill/connection/__init__.py
pydrill/connection/base.py
pydrill/connection/requests_conn.py
pydrill-0.3.1.dist-info/DESCRIPTION.rst
pydrill-0.3.1.dist-info/METADATA
pydrill-0.3.1.dist-info/RECORD
pydrill-0.3.1.dist-info/WHEEL
pydrill-0.3.1.dist-info/metadata.json
pydrill-0.3.1.dist-info/top_level.txt
tests/__init__.py
tests/conftest.py
tests/test_authentication.py
tests/test_metrics.py
tests/test_options.py
tests/test_profiles.py
tests/test_pydrill_setup.py
tests/test_query.py
tests/test_storage.py
tests/test_threads.py
