Metadata-Version: 2.0
Name: pydrill
Version: 0.3.1
Summary: Python Driver for Apache Drill.
Home-page: https://github.com/PythonicNinja/pydrill
Author: Wojciech Nowak
Author-email: mail@pythonic.ninja
License: MIT
Keywords: pydrill
Platform: UNKNOWN
Classifier: Development Status :: 2 - Pre-Alpha
Classifier: Intended Audience :: Developers
Classifier: License :: OSI Approved :: MIT License
Classifier: Natural Language :: English
Classifier: Programming Language :: Python :: 2
Classifier: Programming Language :: Python :: 2.6
Classifier: Programming Language :: Python :: 2.7
Classifier: Programming Language :: Python :: 3
Classifier: Programming Language :: Python :: 3.3
Classifier: Programming Language :: Python :: 3.4
Classifier: Programming Language :: Python :: 3.5
Classifier: Programming Language :: Python :: 3.6
Requires-Dist: requests
